enthusiast_source_shopify/__init__.py
enthusiast_source_shopify/source.py
enthusiast_source_shopify-1.2.0.dist-info/METADATA
enthusiast_source_shopify-1.2.0.dist-info/WHEEL
enthusiast_source_shopify-1.2.0.dist-info/licenses/LICENSE.md
enthusiast_source_shopify-1.2.0.dist-info/RECORD
