Metadata-Version: 2.4
Name: enthusiast-source-shopify
Version: 1.2.0
Summary: A plugin for Enthusiast that provides a Shopify products importer.
License-File: LICENSE.md
Author: Rafal Cymerys
Author-email: rafal@upsidelab.io
Requires-Python: >=3.10,<4.0
Classifier: Programming Language :: Python :: 3
Classifier: Programming Language :: Python :: 3.10
Classifier: Programming Language :: Python :: 3.11
Classifier: Programming Language :: Python :: 3.12
Classifier: Programming Language :: Python :: 3.13
Classifier: Programming Language :: Python :: 3.14
Requires-Dist: enthusiast-common (>=1.4,<2)
Requires-Dist: shopifyapi (>=12.7.0,<13.0.0)
